{
  "doctors": [
    {
      "name": "ุฏฺฉุชุฑ ูพุฑุณุง ุตุงู",
      "specialty": "ูุงูุง",
      "description": "ูุงูุง",
      "licenseNumber": "48002",
      "address": "ุฑูุจุฑู ูุตู - ุฎุงุจุงู ุฌูุงุฏุงูุงุฆูู ุณุงุฎุชูุงู ูพุฒุดฺฉุงู ุขูุง ุทุจูู ุณูู",
      "workingHours": "ุดูุจู ู ุณู ุดูุจู ุนุตุฑ 15 ุชุง 19",
      "phones": ["46864292"],
      "image": "๐คฑ",
      "rating": 4.7,
      "isFeatured": false
    },
    {
      "name": "ุฏฺฉุชุฑ ุญูุฑู ุฑุฌุจ",
      "specialty": "ูุงูุง",
      "description": "ูุงูุง",
      "licenseNumber": "5511",
      "address": "ูุฑุณุฏู ุจู ฺูุงุฑุฑุงู ฺฏูุฏุฑุฒ - ฺฉ ูพุฑุฏุณ ูุจุด ูพุงฺฉุงู",
      "workingHours": "ูุฑ ุฑูุฒ ูุฑุฏ: 11 ุชุง 13 ุฒูุฌ: 16 ุชุง 19",
      "phones": ["46834547"],
      "image": "๐คฑ",
      "rating": 4.6,
      "isFeatured": false
    },
    {
      "name": "ุฏฺฉุชุฑ ุฑูููุง ฺฉูุงู",
      "specialty": "ูุงูุง",
      "description": "ูุงูุง",
      "licenseNumber": "66015",
      "address": "ุฏุฑูุงูฺฏุงู ููุฑุดุงุฏ ูุฏุณุุดูุฑุง ุฌููุจุุจููุงุฑ ุดูุฏุงุุฎ. ุณุฌุงุฏุุฎ. ุงุณุชููุงู",
      "workingHours": "ุฑูุฒ ูุง ูุฑุฏ ุณุงุนุช 14 ุชุง 19",
      "phones": ["46836138"],
      "image": "๐คฑ",
      "rating": 4.8,
      "isFeatured": false
    },
    {
      "name": "ุฏฺฉุชุฑ ุฒุจุง ุชููุฑ",
      "specialty": "ูุงูุง",
      "description": "ูุงูุง",
      "licenseNumber": "32940",
      "address": "ูุฏุงู ูุฏุณ - ุฏุฑูุงูฺฏุงู 13 ุฑุฌุจ",
      "workingHours": "ุนุตุฑ ุฑูุฒ ูุง ุฒูุฌ",
      "phones": ["46826713"],
      "image": "๐คฑ",
      "rating": 4.5,
      "isFeatured": false
    },
    {
      "name": "ุฏฺฉุชุฑ ุณุญุฑ ุงูุงููู",
      "specialty": "ูุงูุง",
      "description": "ูุงูุง",
      "licenseNumber": "ู-37009",
      "address": "ุงุจุชุฏุง ุทุงููุงู - ุณุงุฎุชูุงู ููุณุงู",
      "workingHours": "ูุฑ ุฑูุฒ ุณุงุนุช 16:30 ุชุง 20:30",
      "phones": ["46894112"],
      "image": "๐คฑ",
      "rating": 4.7,
      "isFeatured": false
    },
    {
      "name": "ุฏฺฉุชุฑ ูุงุทูู ุฏููุฏุงู",
      "specialty": "ูุงูุง",
      "description": "ูุงูุง",
      "licenseNumber": "31242",
      "address": "ุจุนุฏ ุงุฒ ุฎ ุณุฌุงุฏ - ุณูุช ุฑุงุณุช ูุฏุงู - ุจู ุจุณุช ฺฉูุงุฑ ุนูฺฉ ฺุดูฺฉ (ุฒุจุงู ฺฉูุงู ุจุงู)",
      "workingHours": "ุดูุจูุฺฉุดูุจูุ ุฏูุดูุจู ุณุงุนุช 16 ุชุง 18",
      "phones": ["46850615"],
      "image": "๐คฑ",
      "rating": 4.6,
      "isFeatured": false
    },
    {
      "name": "ุฏฺฉุชุฑ ูุฑู ุงุญูุฏ ุฒุฏ",
      "specialty": "ูุงูุง",
      "description": "ูุงูุง",
      "licenseNumber": "3793",
      "address": "ูุฏุงู ูุตู ุฑูุจุฑู ุฏุฑูุงูฺฏุงู ูุงุฏู",
      "workingHours": "ูุฑ ุฑูุฒ ุณุงุนุช 16 ุชุง 20",
      "phones": ["46881328"],
      "image": "๐คฑ",
      "rating": 4.8,
      "isFeatured": false
    },
    {
      "name": "ุฏฺฉุชุฑ ููุญู ูุทู ูู",
      "specialty": "ูุงูุง",
      "description": "ูุงูุง",
      "licenseNumber": "36208",
      "address": "ู ุณุฑููุงุช - ฺฉ ุดูุฏ ุฌุฑุฏู - ุจุงูุง ุนูฺฉ ุณุงุฒ ูฺฏู ุทุจูู ุงูู",
      "workingHours": "ูุฑ ุฑูุฒ ุณุงุนุช 17 ุชุง 20:30",
      "phones": ["46820233"],
      "image": "๐คฑ",
      "rating": 4.7,
      "isFeatured": false
    },
    {
      "name": "ุฏฺฉุชุฑ ูุงุฏุง ุฏุฑููุฏ",
      "specialty": "ูุงูุง",
      "description": "ูุงูุง",
      "licenseNumber": "62474",
      "address": "ู ุณุฑููุงุช - ุณุงุฎุชูุงู ุณูุงูุช",
      "workingHours": "ูพูุฌูุดุจู ูุง ุณุงุนุช 18 ุชุง 20:30 ุงฺฉุซุฑุง ุฑูุฒูุง ูุฑุฏ",
      "phones": [],
      "image": "๐คฑ",
      "rating": 4.5,
      "isFeatured": false
    },
    {
      "name": "ุฏฺฉุชุฑ ูุฏุง ุงฺฉุจุงุชุงู",
      "specialty": "ูุงูุง",
      "description": "ูุงูุง",
      "licenseNumber": "17934",
      "address": "ุฎุงุจุงู ุนุงูู-ุณู ุฑุงู ูุฏุณ-ุฑูุจุฑู ุฏุงุฑูุฎุงูู ูุฑ ุฌุงู-ุณุงุฎุชูุงู ุชุจุฑุฒ ูพูุงฺฉ 104 - ุทุจูู ุงูู- ูุงุญุฏ ุฏู",
      "workingHours": "ูุฑ ุฑูุฒ ุณุงุนุช 16 ุชุง 20",
      "phones": ["46814594"],
      "image": "๐คฑ",
      "rating": 4.6,
      "isFeatured": false
    },
    {
      "name": "ุฏฺฉุชุฑ ุฑูุง ูุจ ุฒุงุฏู",
      "specialty": "ูุงูุง",
      "description": "ูุงูุง",
      "licenseNumber": "35478",
      "address": "ูุฏุงู ูุฏุณ - ุณุงุฎุชูุงู ูพุฒุดฺฉุงู ฺฉุงู - ุทุจูู 5 ุฑูุจุฑู ุฎุงู ุฎุงู",
      "workingHours": "ูุฑ ุฑูุฒ ุณุงุนุช 16 ุชุง 20",
      "phones": ["46068201"],
      "image": "๐คฑ",
      "rating": 4.7,
      "isFeatured": false
    },
    {
      "name": "ุฏฺฉุชุฑ ุงุนุธู ูุชูุญ ุงุตู",
      "specialty": "ูุงูุง",
      "description": "ูุงูุง",
      "licenseNumber": "ู-311",
      "address": "ุณุฑููุงุช - ุฎ ูพุงุณุฏุงุฑุงู - ูุจุด ฺฉูฺู ููุฑู ุณุงุฎุชูุงู ูพุฒุดฺฉุงู ุฏฺฉุชุฑ ุตุฏุฑุงุฆ - ุทุจูู 2",
      "workingHours": "ุฑูุฒ ูุง ุฒูุฌ ุณุงุนุช 9 ุชุง 20",
      "phones": ["46821200"],
      "image": "๐คฑ",
      "rating": 4.8,
      "isFeatured": false
    },
    {
      "name": "ุฏฺฉุชุฑ ุซุฑุง ุฑุญู",
      "specialty": "ูุงูุง",
      "description": "ูุงูุง",
      "licenseNumber": "ู-4138",
      "address": "ุฎ ุทุงููุงู - ูุฌุชูุน ุชุฌุงุฑ ูพุฏุฑ ูุฑฺฉุฒ ูุงูุง ุฑุงุจู ุฏุงุงู",
      "workingHours": "ุฑูุฒ ูุง ุฒูุฌ ุณุงุนุช 16 ุชุง 19",
      "phones": ["46812999"],
      "image": "๐คฑ",
      "rating": 4.6,
      "isFeatured": false
    },
    {
      "name": "ุฏฺฉุชุฑ ุญููุง ุตูุงุฎู",
      "specialty": "ูุงูุง",
      "description": "ูุงูุง",
      "licenseNumber": "35317",
      "address": "ุฎุงุจุงู ุนุงูู-ุณู ุฑุงู ูุฏุณ-ุฑูุจุฑู ุฏุงุฑูุฎุงูู ูพูุงฺฉ 104 - ุทุจูู ุงูู",
      "workingHours": "ูุฑ ุฑูุฒ ุณุงุนุช 9 ุชุง 13",
      "phones": ["46814594"],
      "image": "๐คฑ",
      "rating": 4.5,
      "isFeatured": false
    },
    {
      "name": "ุฏฺฉุชุฑ ุฒูุจ ุฌุนูุฑ",
      "specialty": "ูุงูุง",
      "description": "ูุงูุง",
      "licenseNumber": "ู-12844",
      "address": "ู ุณุฑููุงุช - ุฑูุจุฑู ูุฎุงุจุฑุงุช - ฺฉูฺู ููุฑ ุณุงุฎุชูุงู 110 - ุทุจูู 2 (ูุทุจ ุดุงููพูุฑ ููฺฉ)",
      "workingHours": "ูุฑ ุฑูุฒ ุตุจุญ (ุดูุจูุ ฺฉุดูุจูุุณู ุดูุจูุูพูุฌุดูุจู) ุนุตุฑ (ูุฑ ุฑูุฒ) ุณุงุนุช 17 ุชุง 20",
      "phones": ["46820072"],
      "image": "๐คฑ",
      "rating": 4.7,
      "isFeatured": false
    },
    {
      "name": "ุฏฺฉุชุฑ ุณุงูุงุฒ ุณุฑูุด",
      "specialty": "ูุงูุง",
      "description": "ูุงูุง",
      "licenseNumber": "ู-16350",
      "address": "ูุฏุงู ุณุฑููุงุช - ุจููุงุฑ ุงูุงู ุฎูู -ฺฉ ุฑุถุง ูู-ุณุงุฎุชูุงู ูููุฑุงูุณ - ุท4",
      "workingHours": "ุฑูุฒ ูุง ูุฑุฏ ุงุฒ ุตุจุญ ุชุง 8 ุดุจ - ุฑูุฒ ูุง ุฒูุฌ ุงุฒ ุณุงุนุช 10 ุชุง 15 ุนุตุฑ",
      "phones": ["46063358"],
      "image": "๐คฑ",
      "rating": 4.8,
      "isFeatured": false
    },
    {
      "name": "ุฏฺฉุชุฑ ุดฺฉููู ูุฏุงุช",
      "specialty": "ูุงูุง",
      "description": "ูุงูุง",
      "licenseNumber": "1716",
      "address": "ุดูุฑูุฏุณ ุงูุชูุง ุฎ ุทุงููุงู ุณุงุฎุชูุงู ูพุงุณุงุฑฺฏุงุฏ",
      "workingHours": "ุดูุจู ฺฉุดูุจู ุณู ุดูุจู ฺูุงุฑุดูุจู ุณุงุนุช 16 ุชุง 21 ู ุฏูุดูุจู ุณุงุนุช 11 ุชุง 14",
      "phones": ["46861711-2"],
      "image": "๐คฑ",
      "rating": 4.7,
      "isFeatured": false
    },
    {
      "name": "ุฏฺฉุชุฑ ุดูุฑุจุงูู ุฏููุฏุงู",
      "specialty": "ูุงูุง",
      "description": "ูุงูุง",
      "licenseNumber": "ู-12124",
      "address": "ุจููุงุฑ ุงูุงู ุญุณู - ุฑูุจุฑู ุณู ุฑุงู ุงูุชูุง ุทุงููุงู ุฌูุจ ฺฉูฺู ุดูุฏ ฺฏุฑูุณ ูพูุงฺฉ 6",
      "workingHours": "ุดูุจู ุชุง ฺูุงุฑุดูุจู ุตุจุญ ูุง: 9 ุชุง 14 ุดูุจู ู ฺูุงุฑุดูุจู (ุนุตุฑูุง: 16 ุชุง 18",
      "phones": ["46850063"],
      "image": "๐คฑ",
      "rating": 4.6,
      "isFeatured": false
    },
    {
      "name": "ุฏฺฉุชุฑ ุนุตุฑุขุฒุงุฏ ุนูุฒุงุฏู",
      "specialty": "ูุงูุง",
      "description": "ูุงูุง",
      "licenseNumber": "ู-4467",
      "address": "ุณุฑููุงุช-ฺฉูฺู ุฌุฑุฏู-ุณุงุฎุชูุงู ูพุฒุดฺฉุงู ูุงูุงู ุทุจูู ุงูู ูุงุญุฏ 4",
      "workingHours": "ุณุงุนุช 10:30 ุชุง 18",
      "phones": ["46824455"],
      "image": "๐คฑ",
      "rating": 4.5,
      "isFeatured": false
    },
    {
      "name": "ุฏฺฉุชุฑ ูุฑุจุง ุดุฎ ุฒุงุฏู",
      "specialty": "ูุงูุง",
      "description": "ูุงูุง",
      "licenseNumber": "10222",
      "address": "ุฎ ุนุงูู - ุณู ุฑุงู - ุณูุช ฺูพ - ุจุนุฏ ุงุฒ ุจุงุจุงุทุงูุฑ",
      "workingHours": "ุณุงุนุช 7:00 ุชุง 13:00",
      "phones": ["468504144"],
      "image": "๐คฑ",
      "rating": 4.7,
      "isFeatured": false
    },
    {
      "name": "ุฏฺฉุชุฑ ฺฉุจุฑ ูุงุฏุฑ",
      "specialty": "ูุงูุง",
      "description": "ูุงูุง",
      "licenseNumber": "ู-5653",
      "address": "ุงุจุชุฏุง ุจููุงุฑ ุจูุงุฑุงู - ุฌูุจ ุฏุงุฑูุฎุงูู ุฏฺฉุชุฑ ุตูู - ูพูุงฺฉ 5",
      "workingHours": "ุดูุจู ุชุง ฺูุงุฑุดูุจู ุณุงุนุช 8:30 ุชุง 14:00",
      "phones": ["46887997"],
      "image": "๐คฑ",
      "rating": 4.6,
      "isFeatured": false
    },
    {
      "name": "ุฏฺฉุชุฑ ูุฑู ูุณูู",
      "specialty": "ูุงูุง",
      "description": "ูุงูุง",
      "licenseNumber": "ู-2799",
      "address": "ุจู ูุตู - ฺูุงุฑ ุฑุงู ููุชุญ - ุฑูุจุฑู ุจูุงุฑุณุชุงู 12 ุจููู - ุณุงุฎุชูุงู ุงุจู ุณูุง",
      "workingHours": "ูุฑ ุฑูุฒ (ุจู ุฌุฒ ูพูุฌุดูุจู) ุณุงุนุช 17 ุชุง 20",
      "phones": ["46826639"],
      "image": "๐คฑ",
      "rating": 4.8,
      "isFeatured": false
    },
    {
      "name": "ุฏฺฉุชุฑ ูฺฺฏุงู ูุนู ุฒุงุฏู",
      "specialty": "ูุงูุง",
      "description": "ูุงูุง",
      "licenseNumber": "1390",
      "address": "ู ุณุฑููุงุช - ฺฉ 12 ูุฑูุฑุฏู",
      "workingHours": "ุดูุจู ุชุง ฺูุงุฑุดูุจู ุตุจุญ 10 ุชุง 12 ุนุตุฑ 15:30 ุชุง 18:30",
      "phones": ["46841168"],
      "image": "๐คฑ",
      "rating": 4.7,
      "isFeatured": false
    },
    {
      "name": "ุฏฺฉุชุฑ ููุตูุฑู ุจุงุบ ุฎุงุต",
      "specialty": "ูุงูุง",
      "description": "ูุงูุง",
      "licenseNumber": "9670",
      "address": "ูุฏุงู ูุฏุณ - ูุจุด ุฎ ฺูู - ุฌูุจ ุจุงูฺฉ ุณูพู ุณุงุฎุชูุงู ุฒุชูู",
      "workingHours": "ุฑูุฒูุง ุฒูุฌ ุตุจุญ ู ุนุตุฑ",
      "phones": ["46844677"],
      "image": "๐คฑ",
      "rating": 4.6,
      "isFeatured": false
    },
    {
      "name": "ุฏฺฉุชุฑ ุดุจูู ุณุงุฒุด",
      "specialty": "ูุงูุง",
      "description": "ูุงูุง",
      "licenseNumber": "12003",
      "address": "ุจูุงุฑุณุชุงู 12 ุจููู",
      "workingHours": "ูุฑ ุฑูุฒ ุณุงุนุช 8-13",
      "phones": ["46848101"],
      "image": "๐คฑ",
      "rating": 4.8,
      "isFeatured": false
    },
    {
      "name": "ุฏฺฉุชุฑ ุนุทู ูุทู",
      "specialty": "ูุงูุง",
      "description": "ูุงูุง",
      "licenseNumber": "25734",
      "address": "ูุฏุณ ุดูุฑูุฏุณ- ุฎ ุงูุงู ุฎูู ุฌูุจ ุจุงูฺฉ ูู ุฏุฑูุงูฺฏุงู ุดุจุงูู ุฑูุฒ ุจุฑุฒูู",
      "workingHours": "ููู ุฑูุฒู ุณุงุนุช 11:30",
      "phones": ["46820020"],
      "image": "๐คฑ",
      "rating": 4.5,
      "isFeatured": false
    },
    {
      "name": "ุฏฺฉุชุฑ ูฺฺฏุงู ูุงุณู",
      "specialty": "ูุงูุง",
      "description": "ูุงูุง",
      "licenseNumber": "ู-11091",
      "address": "ุฏุฑูุงูฺฏุงู ุณุงุนุช - ูุฏุงู 9 ุฏ - ุฎ ููุงุตุฏุฑุง",
      "workingHours": "ุฑูุฒ ูุง ุฒูุฌ 11:30 ุงู 3",
      "phones": ["46873532"],
      "image": "๐คฑ",
      "rating": 4.6,
      "isFeatured": false
    },
    {
      "name": "ุฏฺฉุชุฑ ูุงุทูู ูุงุฆู ุงูุฏู",
      "specialty": "ูุงูุง",
      "description": "ูุงูุง",
      "licenseNumber": "14497",
      "address": "ุฏุฑูุงูฺฏุงู ูุงุฏู",
      "workingHours": "ุฑูุฒ ูุง ูุฑุฏ 17-19",
      "phones": ["46883956"],
      "image": "๐คฑ",
      "rating": 4.7,
      "isFeatured": false
    },
    {
      "name": "ุฏฺฉุชุฑ ูุญุจูุจู ูุญุฌูุจุงู",
      "specialty": "ูุงูุง",
      "description": "ูุงูุง",
      "licenseNumber": "36244",
      "address": "ุฏุฑูุงูฺฏุงู ูุงุฏู ู ุฏุฑูุงูฺฏุงู ุงุฑุงู",
      "workingHours": "ูุงุฏู ูุชุบุฑ ู ุงุฑุงู ุฏูุดูุจู ุณู ุดูุจู ูพูุฌุดูุจู ุตุจุญ ูุง",
      "phones": ["46883955"],
      "image": "๐คฑ",
      "rating": 4.6,
      "isFeatured": false
    },
    {
      "name": "ุฏฺฉุชุฑ ุณุงุฑุง ุดุฌุงุน ูพูุฑ",
      "specialty": "ูุงูุง",
      "description": "ูุงูุง",
      "licenseNumber": "19397",
      "address": "ุจููุงุฑ ุจูุงุฑุงูุ ุฑูุจุฑู ูุทุจ ุฏฺฉุชุฑ ุฏุฑูุฒู ุงุฏุฑุณ ุฏูู : ุฏุฑูุงูฺฏุงู ุงุฑุงู",
      "workingHours": "ุดูุจูุ ุณู ุดูุจูุ ฺูุงุฑุดูุจูุ ูพูุฌุดูุจู ุตุจุญ ูุง | ุฏุฑูุงูฺฏุงู ุงุฑุงู: ุดูุจู ู ุณู ุดูุจู ุตุจุญ ูุง",
      "phones": ["46859764"],
      "image": "๐คฑ",
      "rating": 4.8,
      "isFeatured": false
    },
    {
      "name": "ุฏฺฉุชุฑ ุฎุฏุฌู ุงูุดูู",
      "specialty": "ูุงูุง",
      "description": "ูุงูุง",
      "licenseNumber": "43945",
      "address": "ูุฏุงู ุณุงุนุช - ุฎ ุทุงููุงู - ูุจุด ฺฉูฺู ูุนุงุฏ ุจูุฏุงุดุช ุขุฏุฑุณ ุฏูู: ุฏุฑูุงูฺฏุงู ุฒุฏุงู - 30 ูุชุฑ ุดูุงู ุดูุฑุง",
      "workingHours": "ูุฑุฑูุฒ ุตุจุญ ูุง",
      "phones": ["46810062"],
      "image": "๐คฑ",
      "rating": 4.7,
      "isFeatured": false
    },
    {
      "name": "ุฏฺฉุชุฑ ูุณุฑู ุตูุฑ",
      "specialty": "ูุงูุง",
      "description": "ูุงูุง",
      "licenseNumber": "46928",
      "address": "ุฏุฑูุงูฺฏุงู ฺฉุชุง",
      "workingHours": "ููู ุฑูุฒู ุงุฒ ุณุงุนุช 11 ุงู 12:30",
      "phones": ["46827322"],
      "image": "๐คฑ",
      "rating": 4.5,
      "isFeatured": false
    },
    {
      "name": "ุฏฺฉุชุฑ ุฒูุฑุง ูุฑุฑุถุง",
      "specialty": "ูุงูุง",
      "description": "ูุงูุง",
      "licenseNumber": "20990",
      "address": "ูุฏุณ ุดูุฑูุฏุณ-ุณุฑุนูุงุฑุช -ุณุงุฎุชูุงู ูพุฒุดฺฉุงู ฺฉูุงุฑ ูุทุจ ุฏฺฉุชุฑ ูุณุงู ูพุฒุดฺฉ",
      "workingHours": "ุดูุจู ุฏู ุดูุจู ูพูุฌ ุดูุจู",
      "phones": ["46849880"],
      "image": "๐คฑ",
      "rating": 4.6,
      "isFeatured": false
    },
    {
      "name": "ุฏฺฉุชุฑ ููุตูุฑู ุตุงุฏู",
      "specialty": "ูุงูุง",
      "description": "ูุงูุง",
      "licenseNumber": "11794",
      "address": "ูุฏุณ ุดูุฑูุฏุณ-ู ููุนุตุฑ-20 ูุชุฑ ููุนุตุฑ-ูุจุด ฺฉูฺู ฺฏู ุงุณ-ุณุงุฎุชูุงู ฺฏู ุงุณฐฒฒ",
      "workingHours": "ููู ุฑูุฒู 9 ุงู 1:30",
      "phones": ["46818688"],
      "image": "๐คฑ",
      "rating": 4.7,
      "isFeatured": false
    },
    {
      "name": "ุฏฺฉุชุฑ ุณุงุฑุง ูุญูุฏุงู",
      "specialty": "ูุงูุง",
      "description": "ูุงูุง",
      "licenseNumber": "21479",
      "address": "ูุฏุณ ูุฏุงู ูุฏุณุุฏุฑูุงูฺฏุงู 13 ุฑุฌุจ",
      "workingHours": "ุฑูุฒ ูุง ูุฑุฏ 17 ุงู 19",
      "phones": ["46826713"],
      "image": "๐คฑ",
      "rating": 4.6,
      "isFeatured": false
    },
    {
      "name": "ุฏฺฉุชุฑ ููุง ุฑุณุชู ุฒุงูุฏ",
      "specialty": "ูุงูุง",
      "description": "ูุงูุง",
      "licenseNumber": "53331",
      "address": "ูุฏุณ ุดูุฑูุฏุณ ูุฏุงู ุขุฒุงุฏ(ุณุฑููุงุช)ุฎุงุจุงู ุขุฒุงุฏุูุจุด ุฎุงุจุงู ุณุฌุงุฏ ูพุงุณุงฺ ูุญูุฏ ุทุจูู ฺูุงุฑูุูุงุญุฏฑถ",
      "workingHours": "ุดูุจู ุงู ฺูุงุฑุดูุจู ุงุฒ ุณุงุนุช 17 ุงู 20",
      "phones": ["46066927"],
      "image": "๐คฑ",
      "rating": 4.8,
      "isFeatured": false
    },
    {
      "name": "ุฏฺฉุชุฑ ูุฑุฌุงู ูู ุฒุงุฏู",
      "specialty": "ูุงูุง",
      "description": "ูุงูุง",
      "licenseNumber": "37176",
      "address": "ูุฏุณ ุจููุงุฑ ูุตู.ุฎุงุจุงู ููุชุญ ุฌููุจ.ูพูุงฺฉ222.ุทุจูู ุงูู",
      "workingHours": "ููู ุฑูุฒู 11 ุงู 20 ุดุจ",
      "phones": ["46857540"],
      "image": "๐คฑ",
      "rating": 4.7,
      "isFeatured": false
    },
    {
      "name": "ุฏฺฉุชุฑ ุงููุงู ุชูุณู ูุฑ",
      "specialty": "ูุงูุง",
      "description": "ูุงูุง",
      "licenseNumber": "26901",
      "address": "ูุฏุณ ุฎุงุจุงู ุดูุฏ ุฌุฑุฏูุฺฉูฺู ุดูุฏ ูุญููุฏุงูุุฌูุจ ุนูฺฉ ููุตูุฑ.ุฒุฑุฒูู",
      "workingHours": "ุดูุจู ุชุง ฺูุงุฑุดูุจู -ูุฑุฏุตุจุญ ูุง-ุฒูุฌ ุนุตุฑ ูุง",
      "phones": ["46816830"],
      "image": "๐คฑ",
      "rating": 4.6,
      "isFeatured": false
    },
    {
      "name": "ุฏฺฉุชุฑ ูุฑู ุฎุฏุงุดูุงุณ",
      "specialty": "ูุงูุง",
      "description": "ูุงูุง",
      "licenseNumber": "20321",
      "address": "ูุฏุณ ูุฏุงู ูุฏุณ.ุงุจุชุฏุง ฺฉูฺู ูพุฑุณุชู.ุณุงุฎุชูุงู ูพุฒุดฺฉุงู ฺฉุงู.ุทุจูู5.ูุงุญุฏ15",
      "workingHours": "ุฏูุดูุจู ู ฺูุงุฑุดูุจู ุณุงุนุช 17 - ุดูุจู ฺฉุดูุจู ุณู ุดูุจู ู ูพูุฌุดูุจู ุณุงุนุช 11 ุงู 17",
      "phones": ["46068201"],
      "image": "๐คฑ",
      "rating": 4.8,
      "isFeatured": false
    }
  ]
}

